pixe.py
pixe-0.7.3.dist-info/LICENSE
pixe-0.7.3.dist-info/METADATA
pixe-0.7.3.dist-info/WHEEL
pixe-0.7.3.dist-info/entry_points.txt
pixe-0.7.3.dist-info/RECORD
