Metadata-Version: 2.1
Name: pixe
Version: 0.7.3
Summary: A digital helper to keep your files neat and tidy
License: Apache-2.0
Keywords: archive,photos,organize
Author: Chris Wells
Author-email: ping@cwlls.dev
Requires-Python: >=3.11,<4.0
Classifier: Development Status :: 3 - Alpha
Classifier: Environment :: Console
Classifier: License :: OSI Approved :: Apache Software License
Classifier: Programming Language :: Python :: 3
Classifier: Programming Language :: Python :: 3.11
Classifier: Programming Language :: Python :: 3.12
Classifier: Topic :: System :: Archiving
Requires-Dist: Click (>=8.1.3,<9.0.0)
Requires-Dist: Pillow (>=10.3.0,<11.0.0)
Requires-Dist: ffmpeg-python (>=0.2.0,<0.3.0)
Requires-Dist: piexif (>=1.1.3,<2.0.0)
Requires-Dist: pillow-heif (>=0.16.0,<0.17.0)
Requires-Dist: pyexiftool (>=0.5.0,<0.6.0)
Project-URL: homepage, https://cwlls.dev/pixe
Project-URL: repository, https://github.com/cwlls/pixe.git
